simatrix/__init__.py
simatrix/matrix.py
simatrix-0.0.3.dist-info/LICENSE.md
simatrix-0.0.3.dist-info/METADATA
simatrix-0.0.3.dist-info/WHEEL
simatrix-0.0.3.dist-info/top_level.txt
simatrix-0.0.3.dist-info/RECORD
