Metadata-Version: 2.1
Name: simatrix
Version: 0.0.3
Summary: A simple way to generate matrix in Python
Author-email: Piotr Daniel <piotr.daniel4@gmail.com>
License: MIT License
Project-URL: Repository, https://github.com/pino888/simatrix
Project-URL: Issues, https://github.com/pino888/simatrix/issues
Keywords: matrix,matrice,multidimensional,list,generator,list generator,matrix generator,simatrix
Classifier: Programming Language :: Python :: 3
Classifier: License :: OSI Approved :: MIT License
Classifier: Operating System :: OS Independent
Requires-Python: >=3.8
License-File: LICENSE.md
